README.md
setup.cfg
setup.py
smilelogging/__init__.py
smilelogging/logger.py
smilelogging/option.py
smilelogging/slutils.py
smilelogging/utils.py
smilelogging.egg-info/PKG-INFO
smilelogging.egg-info/SOURCES.txt
smilelogging.egg-info/dependency_links.txt
smilelogging.egg-info/requires.txt
smilelogging.egg-info/top_level.txt