Metadata-Version: 2.1
Name: smilelogging
Version: 0.6
Summary: Python logging package for easy reproducible experimenting in research.
Home-page: https://github.com/MingSun-Tse/smilelogging
Download-URL: https://github.com/MingSun-Tse/smilelogging/archive/refs/tags/v0.6.tar.gz
Author: Huan Wang
Author-email: wanghuan@westlake.edu.cn
License: MIT
Keywords: logging,reproducible experimenting
Classifier: Development Status :: 3 - Alpha
Classifier: Intended Audience :: Science/Research
Classifier: Topic :: Software Development :: Build Tools
Classifier: License :: OSI Approved :: MIT License
Classifier: Programming Language :: Python :: 3
